wtf_python/__init__.py
wtf_python/main.py
wtfpython-0.2.1.dist-info/METADATA
wtfpython-0.2.1.dist-info/WHEEL
wtfpython-0.2.1.dist-info/entry_points.txt
wtfpython-0.2.1.dist-info/top_level.txt
wtfpython-0.2.1.dist-info/RECORD
