Metadata-Version: 2.1
Name: wtfpython
Version: 0.2.1
Summary: What the f*ck Python!
Home-page: https://github.com/satwikkansal/wtfpython
Author: Satwik Kansal
Maintainer: Satwik Kansal
Maintainer-email: satwikkansal@gmail.com
License: WTFPL 2.0
Keywords: wtfpython gotchas snippets tricky
Platform: any
Classifier: Development Status :: 4 - Beta
Classifier: Environment :: Console
Classifier: Environment :: MacOS X
Classifier: Environment :: Win32 (MS Windows)
Classifier: Intended Audience :: Science/Research
Classifier: Intended Audience :: Developers
Classifier: Intended Audience :: Education
Classifier: Intended Audience :: End Users/Desktop
Classifier: Operating System :: OS Independent
Classifier: Programming Language :: Python :: 3
Classifier: Programming Language :: Python :: 2
Classifier: Topic :: Documentation
Classifier: Topic :: Education
Classifier: Topic :: Scientific/Engineering
Classifier: Topic :: Software Development
